vfm/BisectionMethod.py
vfm/DelumpingMethod.py
vfm/ExtendCG.py
vfm/FlashCalculation.py
vfm/GammaDistribution.py
vfm/GetDataPure.py
vfm/GetParametersPseudo.py
vfm/HeuristicBinaryInteractions.py
vfm/PengRobinsonCalculation.py
vfm/Plotting_Delumping.py
vfm/Plotting_VFM.py
vfm/PosProcessingData.py
vfm/Simulation_Delumping.py
vfm/Simulation_VFM.py
vfm/Tests.py
vfm/UpdateDataDelumping.py
vfm/UpdateDataVFM.py
vfm/VFM.py
vfm/VFMCalculation.py
vfm/__init__.py
vfm/debugging.py
vfm/main_VFM.py
vfm/main_VFM_var.py
vfm/Data/BDO_Data.csv
vfm/Data/BTPData_updated.csv
vfm/Data/BTP_Data.csv
vfm/Data/CGData.csv
vfm/Data/CGData_updated.csv
vfm/Data/Config_TAGS_PI-Daniel_PIDATALINK.CSV
vfm/Data/Config_TAGS_PI-Daniel_PIDATALINK.xlsx
vfm/Data/Data_BTP_VFM.csv
vfm/Data/Data_Delumping_updated.csv
vfm/Data/EMSO_INPUT_QI_calc_2019_corr_P.csv
vfm/Data/EMSO_INPUT_QI_calc_2019_no_corr.csv
vfm/Data/Dados Gustavo-Sergio/Config_TAGS_PI-Daniel_PIDATALINK.xlsx
vfm/Data/Dados Gustavo-Sergio/Ler_dados_PI_config-Daniel _PIDATALINK_1.xlsx
vfm/Data/Dados Gustavo-Sergio/Ler_dados_PI_config-Daniel _PIDATALINK_1805_1902.CSV
vfm/Data/Dados Gustavo-Sergio/Ler_dados_PI_config-Daniel _PIDATALINK_1904_1912.CSV
vfm/Data/Dados Gustavo-Sergio/Ler_dados_PI_config-Daniel _PIDATALINK_2.xlsx
vfm/Data/Dados Maria Rosa/EMSO_INPUT_Cv_calc.xlsx
vfm/Data/Dados Maria Rosa/EMSO_INPUT_Ql_calc_2019n.xlsx
vfm/Data/Dados Maria Rosa/Ler.txt
vfm/Data/Dados Maria Rosa/BDO/Ler.txt
vfm/Data/Dados Maria Rosa/BDO/2018/2018_01_02.png
vfm/Data/Dados Maria Rosa/BDO/2018/2018_03_02.png
vfm/Data/Dados Maria Rosa/BDO/2018/2018_05_02.png
vfm/Data/Dados Maria Rosa/BDO/2018/2018_07_02.png
vfm/Data/Dados Maria Rosa/BDO/2018/2018_09_02.png
vfm/Data/Dados Maria Rosa/BDO/2018/2018_11_02.png
vfm/Data/Dados Maria Rosa/BDO/2019/2019_01_02.png
vfm/Data/Dados Maria Rosa/BDO/2019/2019_02_02.png
vfm/Data/Dados Maria Rosa/BDO/2019/2019_02_06.png
vfm/Data/Dados Maria Rosa/BDO/2019/2019_02_07.png
vfm/Data/Dados Maria Rosa/BDO/2019/2019_02_09.png
vfm-0.0.7.dist-info/LICENSE
vfm-0.0.7.dist-info/METADATA
vfm-0.0.7.dist-info/WHEEL
vfm-0.0.7.dist-info/top_level.txt
vfm-0.0.7.dist-info/RECORD
