Metadata-Version: 2.1
Name: vfm
Version: 0.0.7
Summary: Virtual Flow Metering - Delumping extension, suitable for the SmartMonitor platform, part of the Petrobras - Replicantes IV project        v.0.05: current working version with full data        v.0.07: version with simplified data_PI (10%)
Home-page: https://github.com/LADES-PEQ/vfm
Author: José Torraca, Daniel Silva
Author-email: j.neto23@imperial.ac.uk, dmsilva@peq.coppe.ufrj.br
Classifier: Programming Language :: Python :: 3
Classifier: License :: OSI Approved :: MIT License
Classifier: Operating System :: OS Independent
Requires-Python: >=3.6
License-File: LICENSE
